{
  "headers": {
    "x-amz-cf-pop": "FRA56-P5",
    "x-amz-version-id": "KKKuO3WxFVK8eIDkqNSo_Sd_bVmaJg24",
    "cross-origin-resource-policy": "same-origin",
    "referrer-policy": "strict-origin-when-cross-origin",
    "vary": "Accept-Encoding, Origin",
    "strict-transport-security": "max-age=63072000; includeSubDomains; preload",
    "content-security-policy": "default-src 'none'; style-src 'unsafe-inline'; sandbox",
    "via": "http/2 edgeproxy-h",
    "x-amz-replication-status": "COMPLETED",
    "x-cache": "Hit from cloudfront",
    "server": "deno/gcp-europe-west3",
    "x-content-type-options": "nosniff",
    "etag": "\"c334744afdded918895b9d0675844c09\"",
    "server-timing": "fetchSource;dur=8",
    "x-amz-cf-id": "vzXSVgYQ9YnPFtA60X0WCghRvlCD5I8Xw-fb9yh5yp5Bpgy09PY1Hg==",
    "accept-ranges": "bytes",
    "x-frame-options": "DENY",
    "age": "15425969",
    "content-length": "121",
    "content-type": "application/typescript; charset=utf-8",
    "cross-origin-opener-policy": "same-origin",
    "cross-origin-embedder-policy": "same-origin",
    "access-control-allow-origin": "*",
    "last-modified": "Fri, 25 Mar 2022 13:32:48 GMT",
    "cache-control": "public, max-age=31536000, immutable",
    "date": "Tue, 16 Jan 2024 06:30:42 GMT"
  },
  "url": "https://deno.land/std@0.132.0/node/_crypto/constants.ts",
  "now": {
    "secs_since_epoch": 1720812611,
    "nanos_since_epoch": 732351188
  }
}